dlabel/__init__.py
dlabel/compose.py
dlabel/main.py
dlabel/traefik.py
dlabel/traefik_conf.py
dlabel/version.py
dlabel-0.2.dist-info/LICENSE
dlabel-0.2.dist-info/METADATA
dlabel-0.2.dist-info/WHEEL
dlabel-0.2.dist-info/entry_points.txt
dlabel-0.2.dist-info/top_level.txt
dlabel-0.2.dist-info/RECORD
